ffmperative/__init__.py
ffmperative/cli.py
ffmperative/interpretor.py
ffmperative/prompts.py
ffmperative/tool_mapping.py
ffmperative/tools.py
ffmperative/utils.py
ffmperative-0.0.7.post1.dist-info/LICENSE
ffmperative-0.0.7.post1.dist-info/METADATA
ffmperative-0.0.7.post1.dist-info/WHEEL
ffmperative-0.0.7.post1.dist-info/entry_points.txt
ffmperative-0.0.7.post1.dist-info/top_level.txt
ffmperative-0.0.7.post1.dist-info/RECORD
