Metadata-Version: 2.1
Name: ffmperative
Version: 0.0.7.post1
License-File: LICENSE
Requires-Dist: numpy
Requires-Dist: pillow
Requires-Dist: requests
Requires-Dist: opencv-python
Requires-Dist: ffprobe-python
Requires-Dist: ffmpeg-python
Requires-Dist: soundfile
